youtube_dl_cli/__init__.py
youtube_dl_cli/cli.py
youtube_dl_cli/download_youtube_video.py
youtube_dl_cli/structured.py
youtube_dl_cli/common/__init__.py
youtube_dl_cli/common/consoleHelper.py
youtube_dl_cli/common/testHelper.py
youtube_dl_cli/common/utils.py
youtube_dl_cli-0.1.2.dist-info/LICENSE
youtube_dl_cli-0.1.2.dist-info/METADATA
youtube_dl_cli-0.1.2.dist-info/WHEEL
youtube_dl_cli-0.1.2.dist-info/entry_points.txt
youtube_dl_cli-0.1.2.dist-info/top_level.txt
youtube_dl_cli-0.1.2.dist-info/RECORD
