Metadata-Version: 2.1
Name: youtube-dl-cli
Version: 0.1.2
Summary: A tool that can download the video from youtube and easier to use.
Home-page: https://github.com/CarsonSlovoka/youtube-dl-cli/tree/master
Author: Carson
Author-email: jackparadise520a@gmail.com
License: Apache-2.0
Download-URL: https://github.com/CarsonSlovoka/youtube-dl-cli/tree/master/tarball/v0.1.2
Keywords: youtube,download
Platform: UNKNOWN
Classifier: Topic :: Multimedia :: Video
Classifier: Topic :: Multimedia :: Video :: Capture
Classifier: Topic :: Multimedia :: Sound/Audio :: Players
Classifier: Topic :: Multimedia :: Sound/Audio :: Players :: MP3
Classifier: Natural Language :: Chinese (Traditional)
Classifier: Natural Language :: English
Classifier: Operating System :: Microsoft
Classifier: Development Status :: 5 - Production/Stable
Classifier: License :: OSI Approved :: Apache Software License
Classifier: Programming Language :: Python :: 3.6
Classifier: Programming Language :: Python :: 3.7
Requires-Python: >=3.6.2,
Requires-Dist: colorama
Requires-Dist: youtube-dl
